text_thief/__init__.py
text_thief/text_thief.py
text_thief-0.0.2.dist-info/METADATA
text_thief-0.0.2.dist-info/WHEEL
text_thief-0.0.2.dist-info/licenses/LICENCE
text_thief-0.0.2.dist-info/RECORD
